LossLib/__init__.py
LossLib/segmentation.py
losslib-1.0.2.dist-info/LICENSE
losslib-1.0.2.dist-info/METADATA
losslib-1.0.2.dist-info/WHEEL
losslib-1.0.2.dist-info/top_level.txt
losslib-1.0.2.dist-info/RECORD
